{
  "row_index": 427,
  "market_id": "241226",
  "slug": "will-tom-brady-play-in-week-one-of-the-2022-nfl-season",
  "question": "Will Tom Brady play in Week 1 of the 2022 NFL season?",
  "event_title": "Will Tom Brady play in Week 1 of the 2022 NFL season?",
  "end_date_limit": "2022-09-22",
  "row_end_date_raw": "2022-09-22",
  "expanded_queries": [
    "Tom Brady Week 1 2022 did he play",
    "Tom Brady 2022 game log Buccaneers Week 1 Sep 2022 box score",
    "site:nfl.com Tom Brady 2022 game log Week 1"
  ],
  "stats": {
    "search_calls": 3,
    "raw_result_count": 30,
    "deduped_result_count": 29
  },
  "evidences": [
    {
      "title": "Tom Brady, Tampa Bay Buccaneers, QB - 2022-23 Splits ...",
      "url": "https://www.cbssports.com/nfl/players/187741/tom-brady/splits/2022/",
      "content": "| 3rd Quarter | 163 | 102 | 62.6 | 900 | 4 | 4 | 40 | 7 | 3 | 75.2 | 3 | 2 | 0.7 | 0 | | 4th Quarter | 219 | 149 | 68.0 | 1405 | 13 | 3 | 57 | 14 | 6 | 99.6 | 13 | -3 | -0.2 | 1 | | Overtime | 16 | 11 | 68.8 | 106 | 0 | 0 | 23 | 1 | 1 | 87.0 | 0 | 0 | 0.0 | 0 | | Last Two Minutes of Half | 116 | 75 | 64.7 | 767 | 7 | 1 | 48 | 9 | 4 | 100.0 | 19 | -10 | -0.5 | 1 | | Fourth Quarter Within 7 | 88 | 55 | 62.5 | 539 | 4 | 0 | 51 | 6 | 3 | 94.8 | 9 | -1 | -0.1 | 1 | [...] | Outdoor Games | 14 | 655 | 441 | 67.3 | 4208 | 22 | 8 | 63 | 44 | 19 | 91.1 | 24 | 2 | 0.1 | 1 | [...] | vs Nfc Teams | 12 | 510 | 341 | 66.9 | 3183 | 15 | 7 | 63 | 31 | 12 | 87.9 | 24 | -5 | -0.2 | 1 |",
      "score": 0.99955577,
      "query": "Tom Brady 2022 game log Buccaneers Week 1 Sep 2022 box score",
      "search_index": 2
    },
    {
      "title": "Tom Brady Week 1 Game By Game Stats | StatMuse",
      "url": "https://www.statmuse.com/nfl/ask/tom-brady-week-1-game-by-game-stats",
      "content": "tom brady week 1 game by game stats. Tom Brady games in Week 1. NAME, DATE, TM, OPP, CMP, ATT, PCT ... 9/11/2022 · TB. @. DAL. 18. 27. 66.7. 212. 7.9. 1. 1. 87.3.",
      "score": 0.9995453,
      "query": "Tom Brady Week 1 2022 did he play",
      "search_index": 1
    },
    {
      "title": "Buccaneers 19-3 Cowboys (Sep 11, 2022) Game Recap - ESPN",
      "url": "https://www.espn.com/nfl/recap/_/gameId/401437644",
      "content": "Brady, who improved to 7-0 against the Cowboys, was 18 of 27 for 212 yards with an interception that didn't amount to much because Prescott and receiver Noah Brown couldn't connect on an easy third-down throw near midfield early in the fourth quarter. The Cowboys did nothing to quiet questions about the receiving group behind CeeDee Lamb, the third-year player who is the new No. 1 target after the offseason trade of Amari Cooper. Lamb had two catches for 29 yards while drawing most of the attention. Noah Brown had five catches for 68 yards, while Prescott finished 14 of 29 for 134 yards with an interception that set up one of the first-half field goals. [...] Brady was in control throughout despite an extended break during training camp to attend to personal issues. The seven-time Super Bowl champ got a big assist from the defense in Todd Bowles' debut as Tampa Bay's coach following three seasons as defensive coordinator. “I always play the game for my team, my teammates and the organization,” Brady said. “Just being around them is something I always enjoy. It keeps me very grounded, very humble. I feel like just one of the guys. Not many places where I can go where I feel like...",
      "score": 0.99847525,
      "query": "Tom Brady 2022 game log Buccaneers Week 1 Sep 2022 box score",
      "search_index": 2
    },
    {
      "title": "Tom Brady - Wikipedia",
      "url": "https://en.wikipedia.org/wiki/Tom_Brady",
      "content": "In Week 1 of the 2011 season, Brady threw for a career-high 517 yards, four touchdowns, and one interception in a 38–24 win over the Dolphins and earned AFC Offensive Player of the Week honors. In the game, he threw a record-tying 99-yard touchdown pass to Wes Welker. Brady won AFC Offensive Player of the Week for the following game against the Chargers. He had 423 yards and three touchdowns in the 35–21 victory. Brady closed out the season being named AFC Offensive Player of the Month for November and December. In addition, he was the Week 16 AFC Offensive Player of the Week. Brady had a statistically successful season, and in the regular season finale against the Bills (a 49–21 win), he became the fourth quarterback to throw for 5,000 yards in a season, finishing with 5,235; although [...] In Week 11, Brady recorded four touchdowns and no interceptions in a 30–17 road win against the 49ers. Those four touchdown passes gave him a total of 444 career regular season touchdown passes with one team, breaking Brett Favre's record with the Green Bay Packers. The following week, Brady completed 30-of-50 passes for 286 yards and two touchdowns in a 22–17 road victory against the Jets....",
      "score": 0.998147,
      "query": "Tom Brady Week 1 2022 did he play",
      "search_index": 1
    },
    {
      "title": "Here's how Brady fared in the Bucs' Week 1 win over ...",
      "url": "https://www.nbcsportsboston.com/nfl/heres-how-brady-fared-in-the-bucs-week-1-win-over-the-cowboys/266065/",
      "content": "NBC Sports Boston # Here's how Brady fared in the Bucs' Week 1 win over the Cowboys #### Published September 11, 2022 • Updated on September 12, 2022 at 9:11 am Scott Zolak and Marc Bertrand react to Tom Brady being ranked #1 on the NFL’s top 100 list. Tom Brady just keeps rolling. The 45-year-old looked like his usual self on Sunday Night Football, leading the Tampa Bay Buccaneers to a 19-3 win over the Dallas Cowboys. The @Buccaneers start their 2022 campaign with a WIN#GoBucs | #NFL pic.twitter.com/5cTo50SXWu Subscribe to NBC Sports Boston's podcast network to hear our Insiders bring you the latest insights on your favorite teams! To begin his 23rd NFL season, Brady completed 18 of 27 passes for 212 yards, one touchdown and one interception. [...] Just before the half, Brady and Jones connected for the biggest gain of the game – a 48-yarder that Brady beautifully sailed over the Dallas defense. According to Next Gen Stats, the pass traveled 57.5 yards through the air – the second-longest competition by air distance since the league began tracking it. JULIO. JONES. 📺: #TBvsDAL on NBC pic.twitter.com/A10FxvXXhq The Bucs finally completed a touchdown drive late in the third quar...",
      "score": 0.9978677,
      "query": "Tom Brady 2022 game log Buccaneers Week 1 Sep 2022 box score",
      "search_index": 2
    },
    {
      "title": "Tom Brady 2022 Stats per Game - NFL - ESPN",
      "url": "https://www.espn.com/nfl/player/gamelog/_/id/2330/tom-brady",
      "content": "| Sun 11/27 | @CLECLE | L 23-17 OT | 29 | 43 | 246 | 67.4 | 5.7 | 2 | 0 | 28 | 3 | 97.6 | 57.1 | 1 | 2 | 2.0 | 0 | 2 | | Mon 12/5 | vsNONO | W 17-16 | 36 | 54 | 281 | 66.7 | 5.2 | 2 | 1 | 22 | 1 | 84.0 | 44.8 | 1 | -1 | -1.0 | 0 | -1 | | Sun 12/11 | @SFSF | L 35-7 | 34 | 55 | 253 | 61.8 | 4.6 | 1 | 2 | 32 | 0 | 63.7 | 35.2 | 2 | 0 | 0.0 | 0 | 1 | | Sun 12/18 | vsCINCIN | L 34-23 | 30 | 44 | 312 | 68.2 | 7.1 | 3 | 2 | 24 | 1 | 92.2 | 41.7 | 2 | 1 | 0.5 | 0 | 1 | | Sun 12/25 | @ARIARI | W 19-16 OT | 32 | 48 | 281 | 66.7 | 5.9 | 1 | 2 | 44 | 0 | 71.6 | 36.4 | 2 | 1 | 0.5 | 0 | 2 | | Sun 1/1 | vsCARCAR | W 30-24 | 34 | 45 | 432 | 75.6 | 9.6 | 3 | 0 | 63 | 3 | 127.3 | 78.5 | 3 | 4 | 1.3 | 1 | 2 | [...] | Sun 10/9 | vsATLATL | W 21-15 | 35 | 52 | 351 | 67.3 | 6.8 | 1 | 0 | 40 | 0 | 92.7 | 52.5 | 3 | -3 | -1.0 | 0 | -1 | | Sun 10/16 | @PITPIT | L 20-18 | 25 | 40 | 243 | 62.5 | 6.1 | 1 | 0 | 28 | 2 | 87.8 | 64.7 | 1 | 0 | 0.0 | 0 | 0 | | Sun 10/23 | @CARCAR | L 21-3 | 32 | 49 | 290 | 65.3 | 5.9 | 0 | 0 | 35 | 1 | 81.2 | 54.7 | 1 | 1 | 1.0 | 0 | 1 | | Thu 10/27 | vsBALBAL | L 27-22 | 26 | 44 | 325 | 59.1 | 7.4 | 1 | 0 | 51 | 3 | 89.7 | 30.6 | 1 | 1 | 1.0 | 0 | 1 | | Sun 11/6 | vsLARLAR |...",
      "score": 0.9961755,
      "query": "Tom Brady Week 1 2022 did he play",
      "search_index": 1
    },
    {
      "title": "Tom Brady Stats",
      "url": "https://www.footballdb.com/players/tom-brady-bradyto01",
      "content": "| 2022 | NFL | Tampa BayTB\") | 1 | 1 | 66 | 35 | 53.0 | 351 | 5.3 | 351.0 | 2 | 3.0 | 1 | 1.5 | 30t | 20 | 2 | 2 | 17 | 72.2 | | | NFL | TOTALS | 48 | 48 | 1,921 | 1,200 | 62.5 | 13,400 | 7.0 | 279.2 | 88 | 4.6 | 40 | 2.1 | 73 | 114 | 26 | 81 | 512 | 89.8 | [...] | 2022 | NFL | Tampa BayTB\") | 17 | 17 | 0 | 0 | 0.00 | 0 | 0 | 1 | 0 | 1 | 0.0 | 0.0 | 0 | 0 | | | NFL | TOTALS | 335 | 333 | 0 | 0 | 0.00 | 0 | 0 | 14 | 0 | 14 | 0.0 | 0.0 | 0 | 0 | [...] | 12/18/22 | TB | vs CIN | 44 | 30 | 68.2 | 312 | 7.1 | 3 | 6.8 | 2 | 4.5 | 24 | 18 | 4 | 1 | 8 | 92.2 | L, 34-23 |",
      "score": 0.9941347,
      "query": "Tom Brady 2022 game log Buccaneers Week 1 Sep 2022 box score",
      "search_index": 2
    },
    {
      "title": "Tom Brady Stats First 9 Games Of 2022 Season | StatMuse",
      "url": "https://www.statmuse.com/nfl/ask/tom-brady-stats-first-9-games-of-2022-season",
      "content": "| 5 | Tom Brady T. Brady | 10/9/2022 | 2022 | TB TB | vs | ATL ATL | 35 | 52 | 67.3 | 351 | 6.8 | 1 | 0 | 92.7 | 1.9 | 0.0 | 0 | 0 | | 6 | Tom Brady T. Brady | 10/16/2022 | 2022 | TB TB | @ | PIT PIT | 25 | 40 | 62.5 | 243 | 6.1 | 1 | 0 | 87.8 | 2.5 | 0.0 | 2 | 14 | | 7 | Tom Brady T. Brady | 10/23/2022 | 2022 | TB TB | @ | CAR CAR | 32 | 49 | 65.3 | 290 | 5.9 | 0 | 0 | 81.2 | 0.0 | 0.0 | 1 | 14 | | 8 | Tom Brady T. Brady | 10/27/2022 | 2022 | TB TB | vs | BAL BAL | 26 | 44 | 59.1 | 325 | 7.4 | 1 | 0 | 89.7 | 2.3 | 0.0 | 3 | 20 | | 9 | Tom Brady T. Brady | 11/6/2022 | 2022 | TB TB | vs | LAR LAR | 36 | 58 | 62.1 | 280 | 4.8 | 1 | 0 | 79.7 | 1.7 | 0.0 | 1 | 8 | | Average | 28.9 | 44.2 | 65.3 | 283.0 | 6.4 | 1.1 | 0.1 | 90.5 | 2.5 | 0.3 | 1.6 | 11.9 | [...] Tom Brady Stats First 9 Games Of 2022 Season | StatMuse Toggle Theme Sign in/up Home NBA FC NHL MLB NFL CFB WNBA PGA Money Scores Trending Trending Sports Trending Money Trending Live Examples Data & Glossary Gallery About Blog Shop Toggle Theme Sign in/up Sign in/up Home NBA FC NHL MLB NFL CFB WNBA PGA Money Scores Trending Trending Sports Trending Money Trending Live Examples Data & Glossary Gallery About Blog Shop Toggle The...",
      "score": 0.99187535,
      "query": "Tom Brady Week 1 2022 did he play",
      "search_index": 1
    },
    {
      "title": "Tom Brady 2022 Stats per Game - NFL",
      "url": "https://www.espn.com/nfl/player/gamelog/_/id/2330/tom-brady",
      "content": "| Sun 10/9 | vsATLATL | W 21-15 | 35 | 52 | 351 | 67.3 | 6.8 | 1 | 0 | 40 | 0 | 92.7 | 52.5 | 3 | -3 | -1.0 | 0 | -1 | | Sun 10/16 | @PITPIT | L 20-18 | 25 | 40 | 243 | 62.5 | 6.1 | 1 | 0 | 28 | 2 | 87.8 | 64.7 | 1 | 0 | 0.0 | 0 | 0 | | Sun 10/23 | @CARCAR | L 21-3 | 32 | 49 | 290 | 65.3 | 5.9 | 0 | 0 | 35 | 1 | 81.2 | 54.7 | 1 | 1 | 1.0 | 0 | 1 | | Thu 10/27 | vsBALBAL | L 27-22 | 26 | 44 | 325 | 59.1 | 7.4 | 1 | 0 | 51 | 3 | 89.7 | 30.6 | 1 | 1 | 1.0 | 0 | 1 | | Sun 11/6 | vsLARLAR | W 16-13 | 36 | 58 | 280 | 62.1 | 4.8 | 1 | 0 | 28 | 1 | 79.7 | 56.0 | 0 | 0 | 0.0 | 0 | 0 | | Sun 11/13 | vsSEASEA | W 21-16 | 22 | 29 | 258 | 75.9 | 8.9 | 2 | 1 | 31 | 0 | 111.0 | 88.0 | 6 | -3 | -0.5 | 0 | 0 | [...] | 2022 Regular Season (TB) | | | Passing | | | | | | | | | | | Rushing | | | | | --- --- --- --- --- --- --- --- --- | Date | OPP | Result | CMP | ATT | YDS | CMP% | AVG | TD | INT | LNG | SACK | RTG | QBR | CAR | YDS | AVG | TD | LNG | | Sun 9/11 | @DALDAL | W 19-3 | 18 | 27 | 212 | 66.7 | 7.9 | 1 | 1 | 48 | 2 | 87.3 | 58.7 | 2 | -1 | -0.5 | 0 | 0 | | Sun 9/18 | @NONO | W 20-10 | 18 | 34 | 190 | 52.9 | 5.6 | 1 | 0 | 41 | 1 | 79.3 | 34.9 | 3 | -2 | -0.7 | 0 | 0 | | Sun 9/25 | vsGBGB...",
      "score": 0.98975134,
      "query": "Tom Brady 2022 game log Buccaneers Week 1 Sep 2022 box score",
      "search_index": 2
    },
    {
      "title": "Tom Brady's Top Plays at the Bye | 2022 Highlights",
      "url": "https://www.buccaneers.com/video/tom-brady-highlights-2022-weeks-1-10-nfl-best-plays",
      "content": "Tampa Bay Buccaneers WR Mike Evans makes a 16-yard catch on third down to surpass 13,000 career receiving yards against the Miami Dolphins in Week 17 of the 2025 NFL season. ### Baker Finds Chris Godwin Jr. for 5-Yard Touchdown | Bucs vs. Dolphins Highlights Tampa Bay Buccaneers QB Baker Mayfield hits Chris Godwin Jr. on third down in the end zone against the Miami Dolphins in Week 17 of the 2025 NFL season. ### Bucs vs. Panthers Full Game Highlights | Tampa Bay Falls 23-20 View plays from the Tampa Bay Buccaneers' game against the Carolina Panthers in Week 16 of the 2025 NFL Season. ### Emeka Egbuka Hauls in 40-Yard Catch | Bucs vs. Panthers Highlights QB Baker Mayfield throws a deep pass to WR Emeka Egbuka against the Carolina Panthers in Week 16 of the 2025 NFL season. [...] Tampa Bay Buccaneers OLB Yaya Diaby gets his seventh sack of the season against the Miami Dolphins in Week 17 of the 2025 NFL season. ### Logan Hall Sacks Quinn Ewers to End Half | Bucs vs. Dolphins Highlights Tampa Bay Buccaneers DL Logan Hall gets a sack before halftime against the Miami Dolphins in Week 17 of the 2025 NFL season. ### Baker Mayfield Connects With Jalen McMillan for 33 Yards | Bucs vs. D...",
      "score": 0.98445636,
      "query": "Tom Brady 2022 game log Buccaneers Week 1 Sep 2022 box score",
      "search_index": 2
    },
    {
      "title": "NFL QB Index, Week 1: Ranking all 32 starters entering ...",
      "url": "https://www.nfl.com/news/nfl-qb-index-week-1-ranking-all-32-starters-entering-2022-season",
      "content": "Awake in the dead of night, I computed that I’ve lived in 14 apartments/homes since Tom Brady was chosen in the sixth round of the 2000 NFL Draft. How many of us have seen our own children grow up during his unprecedented waltz through the wilds of pro football? At 45, Brady is coming off an ageism-busting campaign that saw him whip a league-high 719 passes and top everyone else on this list with 5,316 yards and 43 touchdowns. Then he walked off into the sunset, before returning at sunrise to accept the challenge of a 23rd season. Tampa Bay's banged-up line is problematic, but there’s no more doubting Brady’s arm strength in an attack that plans to air it out from wire to wire. As for hints of off-the-field turbulence -- \"I’m 45 years old, man. There’s a lot of [expletive] going on,” [...] In the hands of \"The Mailman,\" the QB Index became something entirely new all over again. An unrivaled \"tape dog,\" Wess gifted readers with sparkling treasures of nuance. Deeply studied game film would morph into sea poems over the pocket awareness of Tom Brady. A Week 14 writeup of an Aaron Rodgers effort against the wandering Lions would transform into new literature on the state of modern f...",
      "score": 0.9832145,
      "query": "site:nfl.com Tom Brady 2022 game log Week 1",
      "search_index": 3
    },
    {
      "title": "Tom Brady 2022 Situational Stats | NFL.com",
      "url": "https://www.nfl.com/players/tom-brady/stats/situational/2022/",
      "content": "### Quarters | | G | Total | Solo | AST | SCK | SFTY | PDEF | INT | TDS | YDS | AVG | LNG | --- --- --- --- --- --- | 1st Quarter | 17 | 0 | 0 | 0 | 0 | 0 | 0 | 0 | 0 | 0 | 0 | 0 | | 4th Quarter | 16 | 0 | 0 | 0 | 0 | 0 | 0 | 0 | 0 | 0 | 0 | 0 | | 4th Quarter within 7 | 11 | 0 | 0 | 0 | 0 | 0 | 0 | 0 | 0 | 0 | 0 | 0 | | Overtime | 2 | 0 | 0 | 0 | 0 | 0 | 0 | 0 | 0 | 0 | 0 | 0 | | 2nd Quarter | 17 | 0 | 0 | 0 | 0 | 0 | 0 | 0 | 0 | 0 | 0 | 0 | | 3rd Quarter | 16 | 1 | 1 | 0 | 0 | 0 | 0 | 0 | 0 | 0 | 0 | 0 | ### Stadium Surfaces | | G | Total | Solo | AST | SCK | SFTY | PDEF | INT | TDS | YDS | AVG | LNG | --- --- --- --- --- --- | Grass | 14 | 1 | 1 | 0 | 0 | 0 | 0 | 0 | 0 | 0 | 0 | 0 | | Turf | 3 | 0 | 0 | 0 | 0 | 0 | 0 | 0 | 0 | 0 | 0 | 0 | [...] | | G | ATT | COMP | PCT | YDS | AVG | LNG | TD | INT | 1st | 1st% | 20+ | SCK | SCKY | RATE | --- --- --- --- --- --- --- --- | | Ahead | 12 | 148 | 93 | 62.8 | 913 | 6.2 | 48 | 5 | 4 | 47 | 31.8 | 9 | 7 | 55 | 80.2 | | Ahead by 1-8 Points | 12 | 91 | 55 | 60.4 | 541 | 6 | 48 | 1 | 1 | 26 | 28.6 | 6 | 7 | 55 | 76.3 | | Ahead by 9-16 Points | 5 | 55 | 36 | 65.4 | 364 | 6.6 | 40 | 4 | 3 | 21 | 38.2 | 3 | 0 | 0 | 85.7 | | Behind | 15 | 44...",
      "score": 0.98159516,
      "query": "Tom Brady Week 1 2022 did he play",
      "search_index": 1
    },
    {
      "title": "Tom Brady Week 1 Game By Game Stats",
      "url": "https://www.statmuse.com/nfl/ask/tom-brady-week-1-game-by-game-stats",
      "content": "| NFC East | W | L | T | PCT | --- --- | Eagles Eagles - y | 11 | 6 | 0 | .647 | | Cowboys Cowboys - e | 7 | 9 | 1 | | | Commanders Commanders - e | 5 | 12 | 0 | .294 | | Giants Giants - e | 4 | 13 | 0 | | | NFC North | W | L | T | PCT | | Bears Bears - y | 11 | 6 | 0 | .647 | | Packers Packers - w | 9 | 7 | 1 | | | Vikings Vikings - e | 9 | 8 | 0 | | | Lions Lions - e | 9 | 8 | 0 | .529 | | NFC South | W | L | T | PCT | | Panthers Panthers - y | 8 | 9 | 0 | .471 | | Buccaneers Buccaneers - e | 8 | 9 | 0 | .471 | | Falcons Falcons - e | 8 | 9 | 0 | .471 | | Saints Saints - e | 6 | 11 | 0 | .353 | | NFC West | W | L | T | PCT | | Seahawks Seahawks - z\\ | 14 | 3 | 0 | .824 | | Rams Rams - w | 12 | 5 | 0 | .706 | | 49ers 49ers - w | 12 | 5 | 0 | .706 | [...] | 13 | Tom Brady T. Brady | 9/14/2009 | NE NE | vs | BUF BUF | 39 | 53 | 73.6 | 378 | 7.1 | 2 | 1 | 97.8 | 3.8 | 1.9 | 1 | 10 | | 14 | Tom Brady T. Brady | 9/7/2008 | NE NE | vs | KC KC | 7 | 11 | 63.6 | 76 | 6.9 | 0 | 0 | 83.9 | 0.0 | 0.0 | 0 | 0 | | 15 | Tom Brady T. Brady | 9/9/2007 | NE NE | @ | NYJ NYJ | 22 | 28 | 78.6 | 297 | 10.6 | 3 | 0 | 146.6 | 10.7 | 0.0 | 0 | 0 | | 16 | Tom Brady T. Brady | 9/10/2006 | NE NE | vs |...",
      "score": 0.9802808,
      "query": "Tom Brady 2022 game log Buccaneers Week 1 Sep 2022 box score",
      "search_index": 2
    },
    {
      "title": "Packers 14-12 Buccaneers (Sep 25, 2022) Final Score - ESPN",
      "url": "https://www.espn.com/nfl/game/_/gameId/401437607/packers-buccaneers",
      "content": "Watch ESPN ESPN Fantasy # Green Bay Packers @ Tampa Bay Buccaneers GB | | 1 | 2 | 3 | 4 | T | --- --- --- | | Packers GB | 7 | 7 | 0 | 0 | 14 | | Buccaneers TB | 3 | 0 | 3 | 6 | 12 | TB ## Game Leaders Aaron Rodgers Tom Brady Aaron Jones Sr. Leonard Fournette Romeo Doubs Russell Gage Jr. Kenny Clark Logan Hall De'Vondre Campbell Mike Edwards ## Team Stats 315 Total Yards 285 2 Turnovers 2 14 1st Downs 19 8-65 Penalties 6-40 6/15 3rd Down 2/11 0/0 4th Down 1/1 2/3 Red Zone 1/1 33:25 Possession 26:35 ## Game Information Tampa, FL Raymond James Stadium Field Judge:Trawick Boger Down Judge:Derick Bowers Back Judge:Terrence Miles Side Judge:David Meslow Referee:Scott Novak Line Judge:Walt Coleman IV Umpire:Ramon George Raymond James Stadium [...] Umpire:Ramon George Raymond James Stadium ## Rodgers throws for 2 TDs, Packers hold off Brady, Bucs 14-12 Tampa Bay Buccaneers Green Bay Packers Green Bay Packers Tampa Bay Buccaneers Tampa Bay Buccaneers ### Win Probability According to ESPN Analytics ## 2025 Standings | NFC North | W | L | T | PCT | PF | PA | --- --- --- | Chicago | 11 | 6 | 0 | .647 | 441 | 415 | | Green Bay | 9 | 7 | 1 | .559 | 391 | 360 | | Minnesota | 9 | 8 | 0 | .529...",
      "score": 0.9719925,
      "query": "Tom Brady 2022 game log Buccaneers Week 1 Sep 2022 box score",
      "search_index": 2
    },
    {
      "title": "2022 NFL Week 1 Sunday live scores and results - Yahoo Sports",
      "url": "https://sports.yahoo.com/2022-nfl-week-1-sunday-schedule-tv-channels-scores-live-stats-for-49-ers-bears-chiefs-cardinals-and-more-130039454.html",
      "content": "Commanders 28, Jaguars 22 | Stats Sep 9, 2021; Tampa, Florida, USA; Tampa Bay Buccaneers quarterback Tom Brady (12) of the NFL throws the ball against the Dallas Cowboys in the fourth quarter at Raymond James Stadium. Mandatory Credit: Jeremy Reper-USA TODAY Sports Download app from appStore Download app from googlePlay [...] NFL image NFL image ... Fantasy image Fantasy image Watch image Watch image Network image Network image Yahoo Sports Yahoo Sports # 2022 NFL Week 1 Sunday live scores and results: Brady's Buccaneers dominate Cowboys After a wild Sunday featuring missed kicks, overtimes and a tie, the Buccaneers beat the Cowboys on the strength of just one touchdown and four field goals. Go figure. ## Sunday Night Football Buccaneers 19, Cowboys 3 | Stats Tom Brady and Buccaneers struggle to find end zone, but still beat Cowboys ## Sunday's late games: Chiefs 44, Cardinals 21 | Stats Patrick Mahomes had 5 TDs vs. Cardinals, will be just fine without Tyreek Hill Chiefs safety Justin Reid kicks extra point after injury to kicker Harrison Butker Chargers 24, Raiders 19 | Stats [...] Colts 20, Texans 20 | Stats Colts tie Texans after comeback falls short, leading to huge survivo...",
      "score": 0.96124375,
      "query": "Tom Brady Week 1 2022 did he play",
      "search_index": 1
    },
    {
      "title": "Buccaneers QB Tom Brady passes Peyton Manning on ...",
      "url": "https://www.nfl.com/news/nfl-stats-and-records-week-9-buccaneers-qb-tom-brady-passes-peyton-manning-on-pa",
      "content": "## NFL Research # NFL stats and records, Week 9: Buccaneers QB Tom Brady passes Peyton Manning on path to 100,000 yards Author Image Senior Researcher NFL Research offers the best nuggets from each week of games in the NFL. Here are the most eye-popping statistical accomplishments of Week 9 of the 2022 NFL season. 1) Tom Brady sets game-winning drive record on way to 100,000 pass yards [...] Fields had a field day against the Dolphins, despite coming out on the wrong end of the scoreboard. The second-year quarterback had 178 rushing yards in Week 9, the most by a QB in modern NFL history (since at least 1935). The previous record was held by Michael Vick, who had 173 yards against the Vikings in Week 13, 2002. Fields' 408 rushing yards since Week 6 trail only Travis Etienne (465), Derrick Henry (462) and Kenneth Walker (424). Fields also hurt the Dolphins through the air and became the only player since at least 1950 with at least 150 rushing yards and three passing scores in the same game. As a team, the Bears rushed for at least 225 yards in their fourth consecutive game, the first team to do so since the 1976 Steelers. [...] After turning the ball over on downs at the Rams' 6...",
      "score": 0.9591543,
      "query": "site:nfl.com Tom Brady 2022 game log Week 1",
      "search_index": 3
    },
    {
      "title": "Purdy outshines Brady in 1st start as 49ers beat Bucs 35-7",
      "url": "https://www.espn.com/nfl/recap?gameId=401437897",
      "content": "Brady, playing just his second road game against the team he rooted for while growing up in nearby San Mateo, was intercepted again on the next possession by Dre Greenlaw and didn't lead the Bucs to a score until a deflected TD pass to Russell Gage late in the third quarter. Brady finished 34 for 55 for 253 yards with one TD and the two interceptions. “It's easy to say everyone's got to play better, but we're just not playing,” Brady said. “We have just not played consistently well very often. We haven't played it for four quarters. Maybe we played it a little bit at times but not today at all.” Despite the lackluster performance, the Bucs still have a one-game lead over Atlanta and Carolina in the NFC South and are in line for a home playoff game if they close it out. [...] Watch ESPN ESPN Fantasy # Tampa Bay Buccaneers @ San Francisco 49ers TB | | 1 | 2 | 3 | 4 | T | --- --- --- | | Buccaneers TB | 0 | 0 | 7 | 0 | 7 | | 49ers SF | 7 | 21 | 7 | 0 | 35 | SF # Purdy outshines Brady in 1st start as 49ers beat Bucs 35-7 SANTA CLARA, Calif. -- — Brock Purdy's day started with a botched audible that led to a crushing hit and ended with an emotional hug with his family and congratulat...",
      "score": 0.9559813,
      "query": "Tom Brady 2022 game log Buccaneers Week 1 Sep 2022 box score",
      "search_index": 2
    },
    {
      "title": "NFL QB Index, Week 10: Tom Brady reclaims No. 1 spot",
      "url": "https://www.nfl.com/news/nfl-qb-index-week-10-2021-season-rankings",
      "content": "On a week-to-week, snap-to-snap basis, I give Brady the slight edge through the first half of the season as the best quarterback in football. It's close at the top, but Brady's availability and consistency is better than the field. He spoke last year about solving some of the Bucs' offensive problems during their 2020 bye week, so I'm curious to see what this group looks like after a week off. Lamar Jackson 2021 stats: 8 games | 65.0 pct | 2,209 pass yds | 8.3 ypa | 13 pass TD | 7 INT | 600 rush yds | 2 rush TD | 5 fumbles [...] Credit Stafford for understanding where he fell short on Sunday night. He chastised himself for spotting the Titans 14 points with picks and holding the ball too long in an effort to make big plays. I don't think Sean McVay will suddenly scrap the dropback passing game that Stafford has excelled at just because of one poor outing, but Los Angeles clearly had the wrong game plan against Tennessee. Physical fronts could continue to give the Rams' offensive line problems. Justin Herbert 2021 stats: 8 games | 66.1 pct | 2,350 pass yds | 7.4 ypa | 18 pass TD | 6 INT | 95 rush yds | 2 rush TD | 1 fumble [...] This is why I push back against too much MVP talk b...",
      "score": 0.9532751,
      "query": "site:nfl.com Tom Brady 2022 game log Week 1",
      "search_index": 3
    },
    {
      "title": "Bucs' Tom Brady sets single-season mark for attempts, ...",
      "url": "https://www.nfl.com/news/nfl-stats-and-records-week-18-bucs-tom-brady-sets-single-season-mark-for-attempt",
      "content": "## NFL Research # NFL stats and records, Week 18: Bucs' Tom Brady sets single-season mark for attempts, completions Author Image Senior Researcher NFL Research offers the best nuggets from each week of games in the NFL. Here are the most eye-popping statistical accomplishments from Week 18 of the 2022 NFL season. 1) Patrick Mahomes sets record for offensive yards in a season [...] Despite suffering the first losing season of his career, Brady still found a way to break another NFL record. Brady finished 2022 with 490 completions and 733 pass attempts, both the most in a single season in NFL history. The 45-year-old and the Buccaneers will host the Cowboys during Super Wild Card Weekend. Brady is 7-0 in his career against Dallas. 5) Brock Purdy moves to 5-0 in his career [...] Mahomes finished 2022 with 5,614 offensive yards, passing Drew Brees for the most in a single season in NFL history. Brees set the previous record with 5,562 in 2011. Mahomes compiled the record with 5,250 passing, 358 rushing, and 6 receiving yards (a completion to himself) this season. The passing total was the fourth-most in NFL history behind seasons by Peyton Manning (2013), Brees (2011) and ﻿Tom Brady...",
      "score": 0.9437636,
      "query": "site:nfl.com Tom Brady 2022 game log Week 1",
      "search_index": 3
    },
    {
      "title": "Tom Brady Stats | The Football Database",
      "url": "https://www.footballdb.com/players/tom-brady-bradyto01",
      "content": "| 2018 | NFL | New EnglandNE\") | 2 | 2 | 44 | 31 | 70.5 | 274 | 6.2 | 137.0 | 2 | 4.5 | 0 | 0.0 | 23 -- | 0 | 0 | 101.9 | | 2019 | NFL | New EnglandNE\") | 1 | 1 | 12 | 8 | 66.7 | 75 | 6.2 | 75.0 | 0 | 0.0 | 0 | 0.0 | 19 | 2 | 0 | 0 | 0 | 83.7 | | 2020 | NFL | Tampa BayTB\") | 0 | 0 | 0 | 0 | 0.0 | 0 | 0.0 | 0.0 | 0 | 0.0 | 0 | 0.0 | 0 | 0 | 0 | 0 | 0 | 0.0 | | 2021 | NFL | Tampa BayTB\") | 2 | 2 | 16 | 12 | 75.0 | 163 | 10.2 | 81.5 | 1 | 6.2 | 0 | 0.0 | 32 | 10 | 3 | 1 | 8 | 127.9 | | 2022 | NFL | Tampa BayTB\") | 1 | 1 | 8 | 6 | 75.0 | 44 | 5.5 | 44.0 | 0 | 0.0 | 0 | 0.0 | 20 | 2 | 1 | 0 | 0 | 87.5 | | | NFL | TOTALS | 19 | 17 | 583 | 385 | 66.0 | 4,463 | 7.7 | 234.9 | 35 | 6.0 | 15 | 2.6 | 65t | 14 | 4 | 23 | 168 | 98.3 | [...] | 2019 | NFL | New EnglandNE\") | 16 | 16 | 3 | 3 | 0 | 0 | 0 | 0 | 0 | 0 | 0 | 0 | 0/0 | 0/0 | 0 | 0.0 | 18 | | 2020 | NFL | Tampa BayTB\") | 16 | 16 | 3 | 3 | 0 | 0 | 0 | 0 | 0 | 0 | 0 | 0 | 0/0 | 0/0 | 0 | 0.0 | 18 | | 2021 | NFL | Tampa BayTB\") | 17 | 17 | 2 | 2 | 0 | 0 | 0 | 0 | 0 | 0 | 0 | 0 | 0/0 | 0/0 | 0 | 0.0 | 12 | | 2022 | NFL | Tampa BayTB\") | 17 | 17 | 1 | 1 | 0 | 0 | 0 | 0 | 0 | 0 | 0 | 0 | 0/0 | 0/0 | 0 | 0.0 | 6 | | | NFL | TOTALS | 335 | 33...",
      "score": 0.937669,
      "query": "Tom Brady Week 1 2022 did he play",
      "search_index": 1
    },
    {
      "title": "Tom Brady 2001 Logs Stats",
      "url": "https://www.nfl.com/players/tom-brady/stats/logs/2001/",
      "content": "| 4 | 10/07/2001 | @Dolphins | L 10 - 30 | 12 | 24 | 86 | 3.6 | 0 | 0 | 4 | 17 | 58.7 | 2 | 9 | 4.5 | 0 | 2 | 2 | | 3 | 09/30/2001 | Colts | W 44 - 13 | 13 | 23 | 168 | 7.3 | 0 | 0 | 1 | 9 | 79.6 | 1 | 2 | 2 | 0 | | | | 2 | 09/23/2001 | Jets | L 3 - 10 | 5 | 10 | 46 | 4.6 | 0 | 0 | 0 | 0 | 62.9 | 1 | 9 | 9 | 0 | | | | 1 | 09/09/2001 | @Bengals | L 17 - 23 | | | | | | | | | | | | | | | | [...] | 11 | 11/25/2001 | Saints | W 34 - 17 | 19 | 26 | 258 | 9.9 | 4 | 0 | 4 | 17 | 143.9 | 4 | 14 | 3.5 | 0 | 2 | 0 | | 10 | 11/18/2001 | Rams | L 17 - 24 | 19 | 27 | 185 | 6.8 | 1 | 2 | 2 | 6 | 70.8 | 2 | 6 | 3 | 0 | | | | 9 | 11/11/2001 | Bills | W 21 - 11 | 15 | 21 | 107 | 5.1 | 1 | 1 | 7 | 36 | 78.9 | 4 | -1 | -0.2 | 0 | 2 | 1 | | 8 | 11/04/2001 | @Falcons | W 24 - 10 | 21 | 31 | 250 | 8.1 | 3 | 0 | 3 | 14 | 124.4 | 3 | 0 | 0 | 0 | | | | 7 | 10/28/2001 | @Broncos | L 20 - 31 | 25 | 38 | 203 | 5.3 | 2 | 4 | 2 | 20 | 57.1 | 2 | -1 | -0.5 | 0 | 1 | 0 | | 6 | 10/21/2001 | @Colts | W 38 - 17 | 16 | 20 | 202 | 10.1 | 3 | 0 | 0 | 0 | 148.3 | 2 | -2 | -1 | 0 | | | | 5 | 10/14/2001 | Chargers | W 29 - 26 | 33 | 54 | 364 | 6.7 | 2 | 0 | 3 | 19 | 93.4 | 1 | 0 | 0 | 0 | 2 | 0 | [...] | WK | Game Date...",
      "score": 0.936285,
      "query": "site:nfl.com Tom Brady 2022 game log Week 1",
      "search_index": 3
    },
    {
      "title": "Tom Brady 2014 Logs Stats",
      "url": "https://www.nfl.com/players/tom-brady/stats/logs/2014/",
      "content": "| WK | Game Date | OPP | RESULT | COMP | ATT | YDS | AVG | TD | INT | SCK | SCKY | RATE | ATT | YDS | AVG | TD | FUM | LOST | --- --- --- --- --- --- --- --- --- | 17 | 12/28/2014 | Bills | L 9 - 17 | 8 | 16 | 80 | 5 | 0 | 0 | 1 | 7 | 64.6 | 2 | 9 | 4.5 | 0 | | | | 16 | 12/21/2014 | @Jets | W 17 - 16 | 23 | 35 | 182 | 5.2 | 1 | 1 | 4 | 36 | 76.1 | 7 | 10 | 1.4 | 0 | | | | 15 | 12/14/2014 | Dolphins | W 41 - 13 | 21 | 35 | 287 | 8.2 | 2 | 1 | 0 | 0 | 93.4 | 3 | 18 | 6 | 0 | | | | 14 | 12/07/2014 | @Chargers | W 23 - 14 | 28 | 44 | 317 | 7.2 | 2 | 1 | 1 | 7 | 90.8 | 4 | 7 | 1.8 | 0 | | | | 13 | 11/30/2014 | @Packers | L 21 - 26 | 22 | 35 | 245 | 7 | 2 | 0 | 1 | 9 | 102.7 | 1 | -1 | -1 | 0 | | | [...] | 12 | 11/23/2014 | Lions | W 34 - 9 | 38 | 53 | 349 | 6.6 | 2 | 1 | 0 | 0 | 94 | | | | | | | | 11 | 11/16/2014 | @Colts | W 42 - 20 | 19 | 30 | 257 | 8.6 | 2 | 2 | 0 | 0 | 85 | 2 | -2 | -1 | 0 | | | | 9 | 11/02/2014 | Broncos | W 43 - 21 | 33 | 53 | 333 | 6.3 | 4 | 1 | 1 | 1 | 97.4 | 2 | 4 | 2 | 0 | | | | 8 | 10/26/2014 | Bears | W 51 - 23 | 30 | 35 | 354 | 10.1 | 5 | 0 | 0 | 0 | 148.4 | 2 | 0 | 0 | 0 | 1 | 0 | | 7 | 10/16/2014 | Jets | W 27 - 25 | 20 | 37 | 261 | 7 | 3 | 0 | 1 | 1 |...",
      "score": 0.9284088,
      "query": "site:nfl.com Tom Brady 2022 game log Week 1",
      "search_index": 3
    },
    {
      "title": "Rams 30-27 Buccaneers (Jan 23, 2022) Game Recap - ESPN",
      "url": "https://www.espn.com/nfl/recap?gameId=401326634",
      "content": "Brady, meanwhile, completed 30 of 54 passes for 329 yards, one touchdown and one interception. He was sacked three times and lost a fumble. Fournette also scored on a 1-yard run for Tampa Bay, which pulled within 27-20 on Brady's 55-yard TD throw to [Mike Evans,]( who made the catch with Jalen Ramsey in pursuit with 3:20 left. “A lot of guys made a bunch of different plays to get us back into it,\" Brady said. \"We got behind. They made us pretty one-dimensional. We showed a lot of fight. But at the end of the day, when you lose a game you lose a game.” The Bucs (14-5), who lost to the Rams for third time in two seasons, were trying to become the first team to repeat as Super Bowl champions since the Brady-led New England Patriots during the 2004 season. [...] Brady rallied the Bucs from a 27-3 second-half deficit with help from three of the Rams’ four turnovers, tying the game on Leonard Fournette’s 9-yard run on fourth-and-inches with 42 seconds remaining. The NFL’s all-time passer leader didn’t get an opportunity to finish the job. And it’s uncertain if that was the final game for Brady, who’s undecided on retirement. “I haven’t put a lot of thought into it,” said the 44-year-o...",
      "score": 0.9005298,
      "query": "Tom Brady Week 1 2022 did he play",
      "search_index": 1
    },
    {
      "title": "Tom Brady Stats, News and Video - QB",
      "url": "https://www.nfl.com/players/tom-brady/",
      "content": "The Patriots will welcome Tom Brady back to Foxborough for their 2023 home opener -- as a fan. Pats owner Robert Kraft told NFL Network's \"Good Morning Football\" on Thursday that he's invited TB12 back to New England to honor the legendary QB. ### NFL QB Index: Ranking all 68 starting quarterbacks from the 2022 NFL season Marc Sessler evaluated every quarterback who started a game (including the playoffs) during the 2022 NFL season to create a complete ranking from 1 to 68. ### Tom Brady says he hopes Aaron Rodgers doesn't retire: 'The league needs good quarterbacks' Tom Brady is a week into his own retirement, so he has thoughts on whether Aaron Rodgers should join him on the other side. On Brady's latest podcast episode, Brady said he hopes Rodgers keeps his career going for now. [...] The Patriots held a special ceremony honoring Tom Brady during halftime of the team's season-opening loss to the Eagles, and there wasn't an empty seat as Brady addressed the packed crowd at Gillette Stadium. ### Tom Brady sees 'invigorated' Aaron Rodgers after trade to Jets: 'I think he's gonna have a great year' Speaking on his \"Let's Go!\" podcast, retired quarterback Tom Brady says he sees an...",
      "score": 0.8840393,
      "query": "site:nfl.com Tom Brady 2022 game log Week 1",
      "search_index": 3
    },
    {
      "title": "2022 NFL season, Week 1: What We Learned from ...",
      "url": "https://www.nfl.com/news/2022-nfl-season-week-1-what-we-learned-from-sunday-s-games",
      "content": "For a second time in franchise history, the Seahawks reside atop the NFL world. Seattle defeated the Patriots on the game's biggest stage, righting a loss suffered against the same organization 11 years ago in Super Bowl XLIX. ### 2026 Pro Bowl Games: What We Learned from NFC's 66-52 win NFL.com breaks down what you need to know from all of Tuesday's action at the Pro Bowl Games skills competition. ### Rams-Seahawks on Championship Sunday: What We Learned from Seattle's 31-27 win Sam Darnold and the NFC's top-seeded Seahawks fended off the NFC-rival Los Angeles Rams to win Sunday's NFC Championship Game. ### Patriots-Broncos on Championship Sunday: What We Learned from New England's 10-7 win [...] Kansas City Chiefs Arizona Cardinals FULL BOX SCORE Kevin Patra's takeaways: Next Gen stat of the game: Patrick Mahomes generated a 110.6 passer rating versus 2-high safety shell (career-low 85.8 passer rating on such snaps in 2021). NFL Research: Patrick Mahomes is one of six players in NFL history with at least six career games with 5-plus pass TDs. He has played in 64 career games. The others played in at least 240-plus career games: Drew Brees, Tom Brady, Peyton Manning, Ben Roethl...",
      "score": 0.8509647,
      "query": "site:nfl.com Tom Brady 2022 game log Week 1",
      "search_index": 3
    },
    {
      "title": "NFL stats and records, Week 1: Patrick Mahomes the ...",
      "url": "https://www.nfl.com/news/nfl-stats-and-records-week-1-patrick-mahomes-the-greatest-week-1-qb-ever",
      "content": "The person who may have noticed Adams' performance most? His former teammate ﻿Aaron Rodgers﻿. Packers wide receivers had fewer receiving yards (120) for the two-time reigning MVP than Adams did for his former college teammate ﻿Derek Carr﻿ (141). ﻿Lamar Jackson, all he does is win Despite the abundance of doubt entering this season, Jackson wins football games. Entering 2022, the Ravens QB had the third-highest win percentage (.755) since the 1970 merger among quarterbacks with at least 25 starts -- behind ﻿Patrick Mahomes﻿ (.794) and ﻿Tom Brady﻿ (.755). The Ravens' Week 1 win over the Jets was Jackson's 38th dub in 50 career starts. Since the merger, only Hall of Famer Ken Stabler and Mahomes (a future Hall of Famer) have put more ones in the win column over that span of starts. [...] ## NFL Research # NFL stats and records, Week 1: Patrick Mahomes the greatest Week 1 QB ever? Author Image Senior Researcher NFL Research offers the best nuggets from each week of games in the NFL. Here are the most eye-popping statistical accomplishments of Week 1 of the 2022 NFL season. ﻿Patrick Mahomes﻿ continues Week 1 dominance against Cardinals Not only does Mahomes have the most touchdowns (...",
      "score": 0.8479678,
      "query": "site:nfl.com Tom Brady 2022 game log Week 1",
      "search_index": 3
    },
    {
      "title": "2022 NFL preseason, Week 1: What We Learned from ...",
      "url": "https://www.nfl.com/news/2022-nfl-preseason-week-1-what-we-learned-from-saturday-s-games",
      "content": "The New England Patriots are advancing to the AFC Championship Game after beating the Houston Texans, 28-16, on Sunday. ### Niners-Seahawks on Divisional Round Saturday: What We Learned from Seattle's 41-6 win The Seattle Seahawks are advancing to the NFC Championship Game after handling the San Francisco 49ers, 41-6, on Saturday night. ### Bills-Broncos on Divisional Round Saturday: What We Learned from Denver's 33-30 overtime win The Denver Broncos are advancing to the AFC Championship Game after a 33-30 overtime win over the Buffalo Bills on Saturday. [...] Sam Darnold and the NFC's top-seeded Seahawks fended off the NFC-rival Los Angeles Rams to win Sunday's NFC Championship Game. ### Patriots-Broncos on Championship Sunday: What We Learned from New England's 10-7 win Buoyed by a stellar defensive effort, quarterback Drake Maye and the Patriots edged backup QB Jarrett Stidham and the Broncos on a snowy and swirling afternoon in Denver. ### Rams-Bears on Divisional Round Sunday: What We Learned from Los Angeles' 20-17 overtime win The Los Angeles Rams are advancing to the NFC Championship Game after beating the Chicago Bears, 20-17, in overtime on Sunday night. ### Texans-Pat...",
      "score": 0.79438496,
      "query": "site:nfl.com Tom Brady 2022 game log Week 1",
      "search_index": 3
    },
    {
      "title": "2022 NFL season, Week 1: What We Learned from Sunday's games",
      "url": "https://www.nfl.com/news/2022-nfl-season-week-1-what-we-learned-from-sunday-s-games",
      "content": "## What We Learned # 2022 NFL season, Week 1: What We Learned from Sunday's games Author Image NFL.com Around The NFL breaks down what you need to know from all of Sunday's action in Week 1 of the 2022 NFL season. Catch up on each game's biggest takeaways using the links below: Tampa Bay Buccaneers Dallas Cowboys FULL BOX SCORE Grant Gordon's takeaways: Next Gen stat of the game: Leonard Fournette averaged 3.0 yards per rush before contact, which was his most in a game in the past five seasons. NFL Research: The Cowboys, who scored their fewest points at home since Week 16 of 2002, tied the 2021 Packers for the fewest points in a season opener by the reigning No. 1 scoring offense in the Super Bowl era. Back to top Kansas City Chiefs Arizona Cardinals FULL BOX SCORE [...] Kansas City Chiefs Arizona Cardinals FULL BOX SCORE Kevin Patra's takeaways: Next Gen stat of the game: Patrick Mahomes generated a 110.6 passer rating versus 2-high safety shell (career-low 85.8 passer rating on such snaps in 2021). NFL Research: Patrick Mahomes is one of six players in NFL history with at least six career games with 5-plus pass TDs. He has played in 64 career games. The others played in at le...",
      "score": 0.5679366,
      "query": "Tom Brady 2022 game log Buccaneers Week 1 Sep 2022 box score",
      "search_index": 2
    },
    {
      "title": "Tom Brady - Tampa Bay Buccaneers Quarterback - ESPN",
      "url": "https://www.espn.com/nfl/player/_/id/2330/tom-brady",
      "content": "Watch ESPN ESPN Fantasy Tom Brady # TomBrady ## Stats ### NFL Quick Links ### Career Passing | | | Stats | | Career | | Passing | | | | | | | | | | Rushing | | | | | --- --- --- --- --- --- --- | CMP | ATT | CMP% | YDS | AVG | TD | INT | LNG | SACK | RTG | CAR | YDS | AVG | TD | LNG | | 7753 | 12050 | 64.3 | 89,214 | 7.4 | 649 | 212 | 99 | 565 | 97.2 | 693 | 1,123 | 1.6 | 28 | 22 | ### Racing Positions [...] ### Racing Positions Brady-led Fanatics event moving out of Saudi Arabia 'LEGENDS': Tom Brady, Devin Booker lead reaction to USA men's hockey gold Drake Maye Jared Goff Reverse? Brady backs Kraft, 'get that 7th ring' Who has won NFL MVP? All-time winners list by year Tom Brady and Vince Wilfork Tom Brady doesn't understand Bill Belichick's HOF snub Brady criticizes snub of Belichick by Hall voters Tom Brady ### Latest Videos ### NFL News 2026 NFL mock drafts: Latest ESPN player, team predictions ## 2026 NFL mock drafts: Latest ESPN player, team predictions 2026 NFL mock draft: Yates' pick predictions in Rounds 1-2 ## 2026 NFL mock draft: Yates' pick predictions in Rounds 1-2 Can 'Tokyo Toe' Kansei Matsuzawa kick his way to the NFL? [...] Can 'Tokyo Toe' Kansei Matsuzawa kick...",
      "score": 0.23091975,
      "query": "Tom Brady Week 1 2022 did he play",
      "search_index": 1
    }
  ],
  "raw_response_meta": [
    {
      "search_index": 1,
      "query": "Tom Brady Week 1 2022 did he play",
      "response_keys": [
        "answer",
        "follow_up_questions",
        "images",
        "query",
        "request_id",
        "response_time",
        "results"
      ],
      "results_count": 10
    },
    {
      "search_index": 2,
      "query": "Tom Brady 2022 game log Buccaneers Week 1 Sep 2022 box score",
      "response_keys": [
        "answer",
        "follow_up_questions",
        "images",
        "query",
        "request_id",
        "response_time",
        "results"
      ],
      "results_count": 10
    },
    {
      "search_index": 3,
      "query": "site:nfl.com Tom Brady 2022 game log Week 1",
      "response_keys": [
        "answer",
        "follow_up_questions",
        "images",
        "query",
        "request_id",
        "response_time",
        "results"
      ],
      "results_count": 10
    }
  ]
}